serialdevicehandler/__init__.py
serialdevicehandler/main.py
serialdevicehandler-1.0.1.dist-info/METADATA
serialdevicehandler-1.0.1.dist-info/WHEEL
serialdevicehandler-1.0.1.dist-info/top_level.txt
serialdevicehandler-1.0.1.dist-info/RECORD
