Metadata-Version: 2.1
Name: serialdevicehandler
Version: 1.0.1
Summary: A python library to run commands on a device via serial port
Home-page: https://github.com/Salliii/serialdevicehandler
Author: Salliii
Keywords: python,library,serial device,serial interface,commands,execute
